eth_bloom/__init__.py
eth_bloom/bloom.py
eth_bloom/py.typed
eth_bloom-3.0.1.dist-info/LICENSE
eth_bloom-3.0.1.dist-info/METADATA
eth_bloom-3.0.1.dist-info/WHEEL
eth_bloom-3.0.1.dist-info/top_level.txt
eth_bloom-3.0.1.dist-info/RECORD
